MANIFEST.in
README.rst
setup.py
apm/__init__.py
apm/cli.py
apm/core.py
apm/exceptions.py
apm/main.py
apm/parser.py
apm/subcommands.py
apm/utils.py
apm/vcs/__init__.py
apm/vcs/collections.py
apm/vcs/components.py
apm/vcs/main.py
arpm.egg-info/PKG-INFO
arpm.egg-info/SOURCES.txt
arpm.egg-info/dependency_links.txt
arpm.egg-info/entry_points.txt
arpm.egg-info/top_level.txt
docs/.DS_Store
docs/Makefile
docs/apm.ansible.rst
docs/apm.rst
docs/apm.vcs.rst
docs/conf.py
docs/index.rst
docs/make.bat
docs/_build/.DS_Store
docs/_build/doctrees/.DS_Store
docs/_build/doctrees/apm.ansible.doctree
docs/_build/doctrees/apm.doctree
docs/_build/doctrees/apm.vcs.doctree
docs/_build/doctrees/environment.pickle
docs/_build/doctrees/index.doctree
docs/_build/doctrees/modules.doctree
docs/_build/doctrees/docs/apm.ansible.doctree
docs/_build/doctrees/docs/apm.doctree
docs/_build/doctrees/docs/apm.vcs.doctree
docs/_build/doctrees/docs/modules.doctree
docs/_build/html/.DS_Store
docs/_build/html/.buildinfo
docs/_build/html/apm.ansible.html
docs/_build/html/apm.html
docs/_build/html/apm.vcs.html
docs/_build/html/genindex.html
docs/_build/html/index.html
docs/_build/html/modules.html
docs/_build/html/objects.inv
docs/_build/html/py-modindex.html
docs/_build/html/search.html
docs/_build/html/searchindex.js
docs/_build/html/_modules/.DS_Store
docs/_build/html/_modules/index.html
docs/_build/html/_modules/apm/home.html
docs/_build/html/_sources/.DS_Store
docs/_build/html/_sources/apm.ansible.txt
docs/_build/html/_sources/apm.txt
docs/_build/html/_sources/apm.vcs.txt
docs/_build/html/_sources/index.txt
docs/_build/html/_sources/modules.txt
docs/_build/html/_sources/docs/apm.ansible.txt
docs/_build/html/_sources/docs/apm.txt
docs/_build/html/_sources/docs/apm.vcs.txt
docs/_build/html/_sources/docs/modules.txt
docs/_build/html/_static/.DS_Store
docs/_build/html/_static/ajax-loader.gif
docs/_build/html/_static/basic.css
docs/_build/html/_static/comment-bright.png
docs/_build/html/_static/comment-close.png
docs/_build/html/_static/comment.png
docs/_build/html/_static/default.css
docs/_build/html/_static/doctools.js
