Metadata-Version: 1.1
Name: arpm
Version: 0.0.3
Summary: ansible package manager command line tool
Home-page: https://github.com/dghubble/apm
Author: Dalton Hubble
Author-email: dghubble@gmail.com
License: UNKNOWN
Platform: UNKNOWN
Classifier: Programming Language :: Python :: 2
Classifier: Programming Language :: Python :: 3
Classifier: License :: OSI Approved :: MIT License
Classifier: Operating System :: POSIX :: Linux
Classifier: Operating System :: MacOS
Classifier: Development Status :: 2 - Pre-Alpha
Classifier: Intended Audience :: Developers
Classifier: Topic :: Software Development :: Build Tools
Provides: apm
